{
  "project_info": {
    "project_number": "1028675094288",
    "project_id": "sample-3952d",
    "storage_bucket": "sample-3952d.appspot.com"
  },
  "client": [
    {
      "client_info": {
        "mobilesdk_app_id": "1:1028675094288:android:460dcf77b14f4a5b364795",
        "android_client_info": {
          "package_name": "com.example.fcm_testing"
        }
      },
      "oauth_client": [
        {
          "client_id": "1028675094288-ucm0ber8koh12etmk6lq6dq9grobvetp.apps.googleusercontent.com",
          "client_type": 3
        }
      ],
      "api_key": [
        {
          "current_key": "AIzaSyDW7Vwrvi8kKzpRim5TP1tSNwSWP_W_mXM"
        }
      ],
      "services": {
        "appinvite_service": {
          "other_platform_oauth_client": [
            {
              "client_id": "1028675094288-ucm0ber8koh12etmk6lq6dq9grobvetp.apps.googleusercontent.com",
              "client_type": 3
            }
          ]
        }
      }
    }
  ],
  "configuration_version": "1"
}